README.md
setup.cfg
setup.py
dbloy/__init__.py
dbloy/cli.py
dbloy/click_types.py
dbloy/util.py
dbloy/version.py
dbloy.egg-info/PKG-INFO
dbloy.egg-info/SOURCES.txt
dbloy.egg-info/dependency_links.txt
dbloy.egg-info/entry_points.txt
dbloy.egg-info/requires.txt
dbloy.egg-info/top_level.txt
dbloy/apply/__init__.py
dbloy/apply/cli.py
dbloy/configure/__init__.py
dbloy/configure/cli.py
test/__init__.py