Metadata-Version: 2.1
Name: dbloy
Version: 0.3.0
Summary: Continuous Delivery tool for PySpark Notebooks based jobs on Databricks.
Home-page: https://github.com/hjh17/dbloy
Author: Hjörtur Hjartarson
Author-email: hjorturh88@gmail.com
Maintainer: Hjörtur Hjartarson
Maintainer-email: hjorturh88@gmail.com
License: ['MIT']
Keywords: databricks cli ci/cd
Platform: UNKNOWN
Classifier: Intended Audience :: Developers
Classifier: Intended Audience :: System Administrators
Classifier: License :: OSI Approved :: MIT License
Classifier: Programming Language :: Python
Classifier: Programming Language :: Python :: 2.6
Classifier: Programming Language :: Python :: 2.7
Classifier: Programming Language :: Python :: 3
Classifier: Programming Language :: Python :: 3.1
Classifier: Programming Language :: Python :: 3.2
Classifier: Programming Language :: Python :: 3.3
Classifier: Programming Language :: Python :: 3.4
Classifier: Programming Language :: Python :: 3.5
Classifier: Programming Language :: Python :: 3.6
